.VERSION
AUTHORS.rst
CONTRIBUTING.rst
HISTORY.rst
LICENSE
MANIFEST.in
Pipfile
Pipfile.lock
README.rst
USAGE.rst
dev-requirements.txt
requirements.txt
setup.cfg
setup.py
docs/Makefile
docs/authors.rst
docs/conf.py
docs/contributing.rst
docs/history.rst
docs/index.rst
docs/installation.rst
docs/modules.rst
docs/readme.rst
docs/toonapilib.rst
docs/usage.rst
toonapilib/.VERSION
toonapilib/AUTHORS.rst
toonapilib/CONTRIBUTING.rst
toonapilib/HISTORY.rst
toonapilib/LICENSE
toonapilib/Pipfile
toonapilib/Pipfile.lock
toonapilib/README.rst
toonapilib/USAGE.rst
toonapilib/__init__.py
toonapilib/_version.py
toonapilib/configuration.py
toonapilib/dev-requirements.txt
toonapilib/helpers.py
toonapilib/requirements.txt
toonapilib/toonapilib.py
toonapilib/toonapilibexceptions.py
toonapilib.egg-info/PKG-INFO
toonapilib.egg-info/SOURCES.txt
toonapilib.egg-info/dependency_links.txt
toonapilib.egg-info/not-zip-safe
toonapilib.egg-info/requires.txt
toonapilib.egg-info/top_level.txt
toonapilib/__pycache__/__init__.cpython-37.pyc
toonapilib/__pycache__/_version.cpython-37.pyc
toonapilib/__pycache__/configuration.cpython-37.pyc
toonapilib/__pycache__/helpers.cpython-37.pyc
toonapilib/__pycache__/toonapilib.cpython-37.pyc
toonapilib/__pycache__/toonapilibexceptions.cpython-37.pyc