Metadata-Version: 1.1
Name: toonapilib
Version: 3.2.3
Summary: A library to interact with eneco's "Toon" smart meter via their official api https://api.toon.eu
Home-page: https://github.com/costastf/toonapilib
Author: Costas Tyfoxylos
Author-email: costas.tyf@gmail.com
License: MIT
Keywords: toonapilib toon eneco
Platform: UNKNOWN
Classifier: Development Status :: 5 - Production/Stable
Classifier: Intended Audience :: Developers
Classifier: License :: OSI Approved :: MIT License
Classifier: Natural Language :: English
Classifier: Programming Language :: Python :: 3.7
